wbutils/__init__.py
wbutils/artifact.py
wbutils/directory.py
wbutils/framework.py
wbutils/include.py
wbutils/io.py
wbutils/keys.py
wbutils/version.py
wbutils/parsing/__init__.py
wbutils/parsing/pytorch.py
wbutils-0.0.4.dist-info/METADATA
wbutils-0.0.4.dist-info/WHEEL
wbutils-0.0.4.dist-info/licenses/LICENSE
wbutils-0.0.4.dist-info/RECORD
