Metadata-Version: 2.1
Name: wbutils
Version: 0.0.4
Summary: Helpful utilities to use Weights & Biases
Project-URL: Homepage, https://github.com/ankur-gupta/wbutils
Project-URL: Repository, https://github.com/ankur-gupta/wbutils.git
Author-email: Ankur Gupta <7110058+ankur-gupta@users.noreply.github.com>
License: MIT License
License-File: LICENSE
Keywords: experiment-tracking,ml,wandb
Classifier: License :: OSI Approved :: MIT License
Classifier: Operating System :: OS Independent
Classifier: Programming Language :: Python :: 3
Requires-Python: >=3.8
Requires-Dist: torch
Requires-Dist: ujson
Requires-Dist: wandb
